[{
  "logId" : 1608249599000,
  "weight" : 198.6,
  "bmi" : 27.81,
  "fat" : 26.600000381469727,
  "date" : "12/17/20",
  "time" : "23:59:59",
  "source" : "API"
},{
  "logId" : 1608335999000,
  "weight" : 198.1,
  "bmi" : 27.75,
  "fat" : 26.399999618530273,
  "date" : "12/18/20",
  "time" : "23:59:59",
  "source" : "API"
},{
  "logId" : 1609804799000,
  "weight" : 198.6,
  "bmi" : 27.81,
  "fat" : 26.5,
  "date" : "01/04/21",
  "time" : "23:59:59",
  "source" : "API"
},{
  "logId" : 1609977599000,
  "weight" : 198.1,
  "bmi" : 27.75,
  "fat" : 26.5,
  "date" : "01/06/21",
  "time" : "23:59:59",
  "source" : "API"
},{
  "logId" : 1610323199000,
  "weight" : 197.5,
  "bmi" : 27.65,
  "fat" : 26.299999237060547,
  "date" : "01/10/21",
  "time" : "23:59:59",
  "source" : "API"
}]